[
  {
    "id": "testando-via-api-1784301779727",
    "titulo": "TESTANDO VIA API",
    "descricao": "FAZENDO UM TESTE DE NOTIFICAÇAO VIA API",
    "categoria": "manutencao",
    "prioridade": "normal",
    "inicio": "2026-07-17T12:22:00-03:00",
    "fim": "2026-07-18T15:22:00-03:00",
    "link": "",
    "mostrarPopup": true,
    "mostrarAvisosGerais": true,
    "piscar": true,
    "ativo": true
  },
  {
    "id": "manutencao-via-api-1784301817934",
    "titulo": "MANUTENÇAO VIA API",
    "descricao": "FAZENDO UMA MANUTENÇAO DE NOTIFICAÇAO VIA API",
    "categoria": "manutencao",
    "prioridade": "urgente",
    "inicio": "2026-07-17T12:22:00-03:00",
    "fim": null,
    "link": "",
    "mostrarPopup": true,
    "mostrarAvisosGerais": true,
    "piscar": true,
    "ativo": true
  },
  {
    "id": "natan-1784317616453",
    "titulo": "NATAN",
    "descricao": "ELE TA NO MERCADO FAZENDO COMPRAS",
    "categoria": "comunicado",
    "prioridade": "importante",
    "inicio": "2026-07-17T16:50:00-03:00",
    "fim": null,
    "link": "",
    "mostrarPopup": true,
    "mostrarAvisosGerais": true,
    "piscar": true,
    "ativo": true
  }
]